klay/__init__.py
klay/builder/__init__.py
klay/builder/builder.py
klay/builder/dag.py
klay/builder/fx_builder.py
klay/cli/__init__.py
klay/cli/export.py
klay/cli/layers.py
klay/cli/types.py
klay/cli/validate.py
klay/core/__init__.py
klay/core/categories.py
klay/core/layer_types.py
klay/core/node.py
klay/core/registry.py
klay/io/__init__.py
klay/io/load_config.py
klay/layers/__init__.py
klay/layers/_arbitrary.py
klay/layers/_atomwise.py
klay/layers/_autograd_forces.py
klay/layers/_base.py
klay/layers/_convnetlayer.py
klay/layers/_e3_transformer.py
klay/layers/_interaction_and_radial_attention.py
klay/layers/_interaction_block.py
klay/layers/_non_linear.py
klay/layers/cutoffs.py
klay/layers/radial_basis.py
klay/layers/egnn/__init__.py
klay/layers/egnn/_egnn.py
klay/layers/embedding/__init__.py
klay/layers/embedding/_binary.py
klay/layers/embedding/_edge.py
klay/layers/embedding/_electronic.py
klay/layers/embedding/_one_hot.py
klay/layers/mace/__init__.py
klay/layers/mace/blocks.py
klay/layers/mace/cg.py
klay/layers/mace/irreps_tools.py
klay/layers/mace/mace_layers.py
klay/layers/mace/scatter.py
klay/layers/mace/symmetric_contraction.py
klay/utils/__init__.py
klay/utils/irreps_helper.py
klay/utils/misc.py
klay/utils/nequip_interaction_block.py
klay-0.9.7.dist-info/METADATA
klay-0.9.7.dist-info/WHEEL
klay-0.9.7.dist-info/entry_points.txt
klay-0.9.7.dist-info/top_level.txt
klay-0.9.7.dist-info/RECORD
