Metadata-Version: 2.4
Name: KLAY
Version: 0.9.7
Summary: A Python package for generating ML layers for MLIPs
Author-email: Amit Gupta <gupta839@umn.edu>
License: MIT License
Project-URL: Homepage, https://github.com/openkim/KLAY
Classifier: Programming Language :: Python :: 3
Classifier: License :: OSI Approved :: MIT License
Classifier: Operating System :: OS Independent
Requires-Python: >=3.9
Requires-Dist: torch
Requires-Dist: torch_runstats
Requires-Dist: e3nn
Requires-Dist: pyyaml
Requires-Dist: networkx
Requires-Dist: omegaconf
Requires-Dist: click
Requires-Dist: rich
Requires-Dist: pydot
Provides-Extra: dev
Requires-Dist: pre-commit>=3.7; extra == "dev"
Requires-Dist: black>=24.4; extra == "dev"
Requires-Dist: isort>=5.13; extra == "dev"
